mztools/__init__.py
mztools/build.py
mztools/common.py
mztools/delete.py
mztools/deploy.py
mztools/get.py
mztools/info.py
mztools/lists.py
mztools/log.py
mztools/put.py
mztools/restart.py
mztools/status.py
mztools/ver.py
mztools/version.py
mztools-1.0.6.data/scripts/mztools
mztools-1.0.6.dist-info/DESCRIPTION.rst
mztools-1.0.6.dist-info/METADATA
mztools-1.0.6.dist-info/RECORD
mztools-1.0.6.dist-info/WHEEL
mztools-1.0.6.dist-info/metadata.json
mztools-1.0.6.dist-info/top_level.txt
