Metadata-Version: 2.0
Name: mztools
Version: 1.0.6
Summary: Digital Route PaaS CLI
Home-page: https://github.com/digitalroute/mztools
Author: Digital Route
Author-email: aws-paas@digitalroute.com
License: MIT
Platform: UNKNOWN
Requires-Dist: boto3
Requires-Dist: termcolor
